MANIFEST.in
README.rst
ez_setup.py
rc_setup.py
setup.py
redcmd/__init__.py
redcmd/__main__.py
redcmd/api.py
redcmd/arg.py
redcmd/cmdfunc.py
redcmd/command_collection.py
redcmd/command_help_formatter.py
redcmd/commandline.py
redcmd/commandparser.py
redcmd/const.py
redcmd/datastore.py
redcmd/decorators.py
redcmd/exc.py
redcmd/func.py
redcmd/main.py
redcmd/maincommand.py
redcmd/subcommand.py
redcmd/version.py
redcmd.egg-info/PKG-INFO
redcmd.egg-info/SOURCES.txt
redcmd.egg-info/dependency_links.txt
redcmd.egg-info/entry_points.txt
redcmd.egg-info/requires.txt
redcmd.egg-info/top_level.txt
redcmd/autocomp/__init__.py
redcmd/autocomp/bash_script_installer.py
redcmd/autocomp/filter.py
redcmd/autocomp/generator.py
redcmd/autocomp/installer.py
redcmd/autocomp/node.py
redcmd/autocomp/option_tree.py
redcmd/autocomp/posh_script_installer.py
redcmd/autocomp/shell_script_installer.py
redcmd/autocomp/shell_script_installer_factory.py
redcmd/autocomp/scripts/bash_autocomp_function.sh
redcmd/client/__init__.py
redcmd/client/__main__.py
redcmd/client/all.py
redcmd/client/autocomp_subcommand.py
redcmd/client/redcmd_internal_subcommand.py
redcmd/test/__init__.py
redcmd/test/__main__.py
redcmd/test/test_datastore.py
redcmd/test/autocomp/__init__.py
redcmd/test/autocomp/dummy.py
redcmd/test/autocomp/maincmd_d.py
redcmd/test/autocomp/maincmd_s.py
redcmd/test/autocomp/subcmd_d.py
redcmd/test/autocomp/subcmd_s.py
redcmd/test/autocomp/test_bash_script_installer.py
redcmd/test/autocomp/test_filter.py
redcmd/test/autocomp/test_generator.py
redcmd/test/autocomp/test_installer.py
redcmd/test/autocomp/test_option_tree.py